plyvel/__init__.py
plyvel/_plyvel.cp39-win_amd64.pyd
plyvel/_version.py
plyvel_win32-1.3.0.dist-info/LICENSE.rst
plyvel_win32-1.3.0.dist-info/METADATA
plyvel_win32-1.3.0.dist-info/WHEEL
plyvel_win32-1.3.0.dist-info/top_level.txt
plyvel_win32-1.3.0.dist-info/RECORD
