Metadata-Version: 2.1
Name: plyvel-win32
Version: 1.3.0
Summary: Plyvel, a fast and feature-rich Python interface to LevelDB
Home-page: https://github.com/AustEcon/plyvel-win32
Author: AustEcon
Author-email: austecon0922@gmail.com
License: BSD License
Download-URL: https://github.com/AustEcon/plyvel-win32/archive/1.3.0.tar.gz
Platform: UNKNOWN
Classifier: Development Status :: 5 - Production/Stable
Classifier: Intended Audience :: Developers
Classifier: Intended Audience :: Information Technology
Classifier: Intended Audience :: Science/Research
Classifier: License :: OSI Approved :: BSD License
Classifier: Operating System :: POSIX
Classifier: Programming Language :: C++
Classifier: Programming Language :: Cython
Classifier: Programming Language :: Python
Classifier: Programming Language :: Python :: 3.7
Classifier: Programming Language :: Python :: 3.8
Classifier: Programming Language :: Python :: 3.9
Classifier: Topic :: Database
Classifier: Topic :: Database :: Database Engines/Servers
Classifier: Topic :: Software Development :: Libraries :: Python Modules
